prepost/__init__.py
prepost/prepost.py
prepost-0.1.8.dist-info/LICENSE
prepost-0.1.8.dist-info/WHEEL
prepost-0.1.8.dist-info/METADATA
prepost-0.1.8.dist-info/RECORD
